tibber_aws/__init__.py
tibber_aws/aws_base.py
tibber_aws/aws_lambda.py
tibber_aws/aws_logs.py
tibber_aws/aws_metadata.py
tibber_aws/aws_queue.py
tibber_aws/s3.py
tibber_aws/secret_manager.py
tibber_aws/sns.py
tibber_aws-0.16.3.dist-info/LICENSE
tibber_aws-0.16.3.dist-info/METADATA
tibber_aws-0.16.3.dist-info/WHEEL
tibber_aws-0.16.3.dist-info/top_level.txt
tibber_aws-0.16.3.dist-info/RECORD
